[
  {
    "tag_name": "entity",
    "ids_to_tags": {
      "1": "B-age",
      "2": "I-age",
      "3": "L-age",
      "4": "U-age",
      "5": "B-country",
      "6": "I-country",
      "7": "L-country",
      "8": "U-country",
      "9": "B-director",
      "10": "I-director",
      "11": "L-director",
      "12": "U-director",
      "13": "B-genre",
      "14": "I-genre",
      "15": "L-genre",
      "16": "U-genre",
      "17": "B-id",
      "18": "I-id",
      "19": "L-id",
      "20": "U-id",
      "21": "B-location",
      "22": "I-location",
      "23": "L-location",
      "24": "U-location",
      "25": "B-movie_title",
      "26": "I-movie_title",
      "27": "L-movie_title",
      "28": "U-movie_title",
      "29": "B-platform",
      "30": "I-platform",
      "31": "L-platform",
      "32": "U-platform",
      "33": "B-rating",
      "34": "I-rating",
      "35": "L-rating",
      "36": "U-rating",
      "0": "O"
    },
    "tags_to_ids": {
      "B-age": 1,
      "I-age": 2,
      "L-age": 3,
      "U-age": 4,
      "B-country": 5,
      "I-country": 6,
      "L-country": 7,
      "U-country": 8,
      "B-director": 9,
      "I-director": 10,
      "L-director": 11,
      "U-director": 12,
      "B-genre": 13,
      "I-genre": 14,
      "L-genre": 15,
      "U-genre": 16,
      "B-id": 17,
      "I-id": 18,
      "L-id": 19,
      "U-id": 20,
      "B-location": 21,
      "I-location": 22,
      "L-location": 23,
      "U-location": 24,
      "B-movie_title": 25,
      "I-movie_title": 26,
      "L-movie_title": 27,
      "U-movie_title": 28,
      "B-platform": 29,
      "I-platform": 30,
      "L-platform": 31,
      "U-platform": 32,
      "B-rating": 33,
      "I-rating": 34,
      "L-rating": 35,
      "U-rating": 36,
      "O": 0
    },
    "num_tags": 37
  }
]